anoseg/__init__.py
anoseg/datasets/__init__.py
anoseg/datasets/dataset.py
anoseg/datasets/imagenet.py
anoseg/datasets/patch_train_dataset.py
anoseg/datasets/test_dataset.py
anoseg/datasets/train_dataset.py
anoseg/datasets/anomaly_creator/__init__.py
anoseg/datasets/anomaly_creator/anomaly_creator.py
anoseg/datasets/anomaly_creator/cutpaste_anomaly_creator.py
anoseg/datasets/anomaly_creator/dfc_anomaly_creator.py
anoseg/datasets/anomaly_creator/ssaps_anomaly_creator.py
anoseg/evaluation/__init__.py
anoseg/evaluation/dfc_metric.py
anoseg/evaluation/eval.py
anoseg/evaluation/iou.py
anoseg/evaluation/pro_metric.py
anoseg/evaluation/roc_metric.py
anoseg/evaluation/util.py
anoseg/models/__init__.py
anoseg/models/utils.py
anoseg/models/DFC/__init__.py
anoseg/models/DFC/model.py
anoseg/models/DFC/backbone/__init__.py
anoseg/models/DFC/backbone/vgg.py
anoseg/models/DFC/backbone/vgg19.py
anoseg/models/DFC/backbone/vgg19_s.py
anoseg/models/DFC/base_dfc/__init__.py
anoseg/models/DFC/base_dfc/tester.py
anoseg/models/DFC/base_dfc/trainer.py
anoseg/models/DFC/patch_dfc/__init__.py
anoseg/models/DFC/patch_dfc/tester.py
anoseg/models/DFC/patch_dfc/trainer.py
anoseg/models/PaDiM/__init__.py
anoseg/models/PaDiM/model.py
anoseg/models/PaDiM/backbone/__init__.py
anoseg/models/PaDiM/backbone/backbone_models.py
anoseg/models/PaDiM/backbone/base.py
anoseg/models/PaDiM/backbone/padim.py
anoseg/models/PaDiM/base_padim/__init__.py
anoseg/models/PaDiM/base_padim/tester.py
anoseg/models/PaDiM/base_padim/trainer.py
anoseg/models/PaDiM/patch_padim/__init__.py
anoseg/models/PaDiM/patch_padim/tester.py
anoseg/models/PaDiM/patch_padim/trainer.py
anoseg/models/PaDiM/utils/__init__.py
anoseg/models/PaDiM/utils/distance.py
anoseg/models/PaDiM/utils/regions.py
anoseg/models/PaDiM/utils/transforms.py
anoseg/models/PaDiM/utils/utils.py
anoseg/models/SPADE/__init__.py
anoseg/models/SPADE/model.py
anoseg/models/SPADE/base_spade/__init__.py
anoseg/models/SPADE/base_spade/tester.py
anoseg-0.0.4.dist-info/METADATA
anoseg-0.0.4.dist-info/WHEEL
anoseg-0.0.4.dist-info/top_level.txt
anoseg-0.0.4.dist-info/RECORD
